atkins/__about__.py
atkins/__init__.py
atkins/base.py
atkins/security.py
atkins/utils.py
atkins/services/__init__.py
atkins/services/activity_logging.py
atkins/services/redeem_code.py
atkins/services/user.py
atkins/services/user_credit.py
atkins/services/user_membership.py
atkins-0.0.4.dist-info/METADATA
atkins-0.0.4.dist-info/WHEEL
atkins-0.0.4.dist-info/licenses/LICENSE.txt
atkins-0.0.4.dist-info/RECORD
